resolve_support.cpython-38-x86_64-linux-gnu.so
resolve/response.py
resolve/polarization_space.py
resolve/version.py
resolve/calibration.py
resolve/cpp2py.py
resolve/__init__.py
resolve/util.py
resolve/sky_model.py
resolve/dirty_image.py
resolve/logger.py
resolve/mpi_operators.py
resolve/fits.py
resolve/irg_space.py
resolve/mpi.py
resolve/polarization_matrix_exponential.py
resolve/extra.py
resolve/correlated_field_model.py
resolve/weighting_model.py
resolve/integrated_wiener_process.py
resolve/simple_operators.py
resolve/config_utils.py
resolve/constants.py
resolve/dtype_converter.py
resolve/likelihood.py
resolve/points.py
resolve/energy_operators.py
resolve/data/observation.py
resolve/data/antenna_positions.py
resolve/data/ms_import.py
resolve/data/__init__.py
resolve/data/direction.py
resolve/data/averaging.py
resolve/data/auxiliary_table.py
resolve/data/polarization.py
resolve/ubik_tools/plot_sky_hdf5.py
resolve/ubik_tools/__init__.py
resolve/ubik_tools/fits.py
resolve/ubik_tools/plot_polarization.py
resolve/mosaicing/single_dish_response.py
resolve/mosaicing/__init__.py
resolve/mosaicing/sky_slicer.py
resolve/plot/__init__.py
resolve/plot/sky.py
resolve/plot/baseline_histogram.py
resolve/library/calibrators.py
resolve/library/__init__.py
resolve/library/meerkat_beam.py
resolve/library/primary_beams.py
resolve/command_line/__init__.py
resolve/command_line/resolve.py
ift_resolve-0.4.dist-info/WHEEL
ift_resolve-0.4.dist-info/top_level.txt
ift_resolve-0.4.dist-info/entry_points.txt
ift_resolve-0.4.dist-info/METADATA
ift_resolve-0.4.dist-info/COPYING
ift_resolve-0.4.dist-info/RECORD
ift_resolve-0.4.dist-info/zip-safe
