Metadata-Version: 2.1
Name: ift-resolve
Version: 0.4
Summary: Radio imaging with information field theory
Home-page: https://gitlab.mpcdf.mpg.de/ift/resolve
Author: Philipp Arras
Author-email: parras@mpa-garching.mpg.de
License: GPLv3
Platform: UNKNOWN
Classifier: Development Status :: 4 - Beta
Classifier: Topic :: Utilities
Classifier: License :: OSI Approved :: GNU General Public License v3 or later (GPLv3+)
Provides-Extra: full
